scrin/__init__.py
scrin/hyper_test_clb_distribution.py
scrin/hyper_test_glb.py
scrin/hyper_test_glb_base.py
scrin/hyper_test_glb_distribution.py
scrin/hyper_test_glb_nocell.py
scrin/main.py
scrin/tools/__init__.py
scrin/tools/result_proc.py
scrin-1.0.6.dist-info/licenses/LICENSE
scrin-1.0.6.dist-info/METADATA
scrin-1.0.6.dist-info/WHEEL
scrin-1.0.6.dist-info/entry_points.txt
scrin-1.0.6.dist-info/top_level.txt
scrin-1.0.6.dist-info/RECORD
