Metadata-Version: 2.4
Name: scrin
Version: 1.0.6
License-File: LICENSE
Requires-Dist: mpi4py
Requires-Dist: numpy
Requires-Dist: scipy
Requires-Dist: pandas
Requires-Dist: scikit-learn
Requires-Dist: pyarrow
Requires-Dist: msgpack
Requires-Dist: statsmodels
Requires-Dist: tqdm
Requires-Dist: rtree
Requires-Dist: tools
Dynamic: license-file
Dynamic: requires-dist
